nonebot_plugin_bililivedm-0.1.5.dist-info/METADATA
nonebot_plugin_bililivedm-0.1.5.dist-info/WHEEL
nonebot_plugin_bililivedm-0.1.5.dist-info/entry_points.txt
nonebot_plugin_bililivedm/.gitattributes
nonebot_plugin_bililivedm/.gitignore
nonebot_plugin_bililivedm/Config.py
nonebot_plugin_bililivedm/__init__.py
nonebot_plugin_bililivedm/blivedm/__init__.py
nonebot_plugin_bililivedm/blivedm/clients/__init__.py
nonebot_plugin_bililivedm/blivedm/clients/open_live.py
nonebot_plugin_bililivedm/blivedm/clients/web.py
nonebot_plugin_bililivedm/blivedm/clients/ws_base.py
nonebot_plugin_bililivedm/blivedm/handlers.py
nonebot_plugin_bililivedm/blivedm/models/__init__.py
nonebot_plugin_bililivedm/blivedm/models/open_live.py
nonebot_plugin_bililivedm/blivedm/models/web.py
nonebot_plugin_bililivedm/blivedm/utils.py
nonebot_plugin_bililivedm/requirements.txt
nonebot_plugin_bililivedm/send_ruler.py
nonebot_plugin_bililivedm-0.1.5.dist-info/RECORD
