Metadata-Version: 2.1
Name: nonebot_plugin_bililivedm
Version: 0.1.5
Summary: 基于ws的b站弹幕监控
Author-Email: STESmly <STESmly@mail.com>
Project-URL: Homepage, https://github.com/STESmly/nonebot_plugin_bililivedm
Project-URL: Repository, https://github.com/STESmly/nonebot_plugin_bililivedm
Requires-Python: <4.0,>=3.8
Requires-Dist: nonebot2>=2.2.1
Requires-Dist: aiohttp>=3.10.10
Requires-Dist: Brotli>=1.1.0
Requires-Dist: yarl>=1.15.2
